{
	"backtraceGraph" : 
	{
		"commands" : 
		[
			"install",
			"cisst_set_package_settings",
			"cisst_unset_all_package_settings"
		],
		"files" : 
		[
			"cmake/cisstInternalMacros.cmake",
			"cisst-dependencies/CMakeLists.txt"
		],
		"nodes" : 
		[
			{
				"file" : 1
			},
			{
				"command" : 1,
				"file" : 1,
				"line" : 25,
				"parent" : 0
			},
			{
				"command" : 0,
				"file" : 0,
				"line" : 56,
				"parent" : 1
			},
			{
				"command" : 0,
				"file" : 0,
				"line" : 65,
				"parent" : 1
			},
			{
				"command" : 1,
				"file" : 1,
				"line" : 27,
				"parent" : 0
			},
			{
				"command" : 0,
				"file" : 0,
				"line" : 56,
				"parent" : 4
			},
			{
				"command" : 0,
				"file" : 0,
				"line" : 65,
				"parent" : 4
			},
			{
				"command" : 1,
				"file" : 1,
				"line" : 84,
				"parent" : 0
			},
			{
				"command" : 0,
				"file" : 0,
				"line" : 56,
				"parent" : 7
			},
			{
				"command" : 0,
				"file" : 0,
				"line" : 65,
				"parent" : 7
			},
			{
				"command" : 1,
				"file" : 1,
				"line" : 84,
				"parent" : 0
			},
			{
				"command" : 0,
				"file" : 0,
				"line" : 56,
				"parent" : 10
			},
			{
				"command" : 0,
				"file" : 0,
				"line" : 65,
				"parent" : 10
			},
			{
				"command" : 1,
				"file" : 1,
				"line" : 84,
				"parent" : 0
			},
			{
				"command" : 0,
				"file" : 0,
				"line" : 56,
				"parent" : 13
			},
			{
				"command" : 0,
				"file" : 0,
				"line" : 65,
				"parent" : 13
			},
			{
				"command" : 1,
				"file" : 1,
				"line" : 84,
				"parent" : 0
			},
			{
				"command" : 0,
				"file" : 0,
				"line" : 56,
				"parent" : 16
			},
			{
				"command" : 0,
				"file" : 0,
				"line" : 65,
				"parent" : 16
			},
			{
				"command" : 1,
				"file" : 1,
				"line" : 84,
				"parent" : 0
			},
			{
				"command" : 0,
				"file" : 0,
				"line" : 56,
				"parent" : 19
			},
			{
				"command" : 0,
				"file" : 0,
				"line" : 65,
				"parent" : 19
			},
			{
				"command" : 1,
				"file" : 1,
				"line" : 84,
				"parent" : 0
			},
			{
				"command" : 0,
				"file" : 0,
				"line" : 56,
				"parent" : 22
			},
			{
				"command" : 0,
				"file" : 0,
				"line" : 65,
				"parent" : 22
			},
			{
				"command" : 2,
				"file" : 1,
				"line" : 102,
				"parent" : 0
			},
			{
				"command" : 0,
				"file" : 0,
				"line" : 87,
				"parent" : 25
			},
			{
				"command" : 0,
				"file" : 1,
				"line" : 118,
				"parent" : 0
			},
			{
				"command" : 1,
				"file" : 1,
				"line" : 240,
				"parent" : 0
			},
			{
				"command" : 0,
				"file" : 0,
				"line" : 56,
				"parent" : 28
			},
			{
				"command" : 0,
				"file" : 0,
				"line" : 65,
				"parent" : 28
			},
			{
				"command" : 1,
				"file" : 1,
				"line" : 241,
				"parent" : 0
			},
			{
				"command" : 0,
				"file" : 0,
				"line" : 56,
				"parent" : 31
			},
			{
				"command" : 0,
				"file" : 0,
				"line" : 65,
				"parent" : 31
			},
			{
				"command" : 1,
				"file" : 1,
				"line" : 257,
				"parent" : 0
			},
			{
				"command" : 0,
				"file" : 0,
				"line" : 56,
				"parent" : 34
			},
			{
				"command" : 0,
				"file" : 0,
				"line" : 65,
				"parent" : 34
			},
			{
				"command" : 1,
				"file" : 1,
				"line" : 259,
				"parent" : 0
			},
			{
				"command" : 0,
				"file" : 0,
				"line" : 56,
				"parent" : 37
			},
			{
				"command" : 0,
				"file" : 0,
				"line" : 65,
				"parent" : 37
			},
			{
				"command" : 1,
				"file" : 1,
				"line" : 263,
				"parent" : 0
			},
			{
				"command" : 0,
				"file" : 0,
				"line" : 56,
				"parent" : 40
			},
			{
				"command" : 0,
				"file" : 0,
				"line" : 65,
				"parent" : 40
			},
			{
				"command" : 0,
				"file" : 1,
				"line" : 277,
				"parent" : 0
			},
			{
				"command" : 1,
				"file" : 1,
				"line" : 369,
				"parent" : 0
			},
			{
				"command" : 0,
				"file" : 0,
				"line" : 56,
				"parent" : 44
			},
			{
				"command" : 0,
				"file" : 0,
				"line" : 65,
				"parent" : 44
			},
			{
				"command" : 1,
				"file" : 1,
				"line" : 370,
				"parent" : 0
			},
			{
				"command" : 0,
				"file" : 0,
				"line" : 56,
				"parent" : 47
			},
			{
				"command" : 0,
				"file" : 0,
				"line" : 65,
				"parent" : 47
			},
			{
				"command" : 1,
				"file" : 1,
				"line" : 371,
				"parent" : 0
			},
			{
				"command" : 0,
				"file" : 0,
				"line" : 56,
				"parent" : 50
			},
			{
				"command" : 0,
				"file" : 0,
				"line" : 65,
				"parent" : 50
			}
		]
	},
	"installers" : 
	[
		{
			"backtrace" : 2,
			"component" : "cisstOpenGL",
			"destination" : "share/cisst-1.3/cmake",
			"paths" : 
			[
				"/home/ytxu/cr_dvrk_ws/build/cisst/share/cisst-1.3/cmake/cisstOpenGLOpenGL.cmake"
			],
			"type" : "file"
		},
		{
			"backtrace" : 3,
			"component" : "cisstOpenGL",
			"destination" : "share/cisst-1.3/cmake",
			"paths" : 
			[
				"/home/ytxu/cr_dvrk_ws/build/cisst/share/cisst-1.3/cmake/cisstOpenGLExternal.cmake"
			],
			"type" : "file"
		},
		{
			"backtrace" : 5,
			"component" : "cisstOpenGL",
			"destination" : "share/cisst-1.3/cmake",
			"paths" : 
			[
				"/home/ytxu/cr_dvrk_ws/build/cisst/share/cisst-1.3/cmake/cisstOpenGLOpenGL.cmake"
			],
			"type" : "file"
		},
		{
			"backtrace" : 6,
			"component" : "cisstOpenGL",
			"destination" : "share/cisst-1.3/cmake",
			"paths" : 
			[
				"/home/ytxu/cr_dvrk_ws/build/cisst/share/cisst-1.3/cmake/cisstOpenGLExternal.cmake"
			],
			"type" : "file"
		},
		{
			"backtrace" : 8,
			"component" : "cisstQt",
			"destination" : "share/cisst-1.3/cmake",
			"paths" : 
			[
				"/home/ytxu/cr_dvrk_ws/build/cisst/share/cisst-1.3/cmake/cisstQtQt5Core.cmake"
			],
			"type" : "file"
		},
		{
			"backtrace" : 9,
			"component" : "cisstQt",
			"destination" : "share/cisst-1.3/cmake",
			"paths" : 
			[
				"/home/ytxu/cr_dvrk_ws/build/cisst/share/cisst-1.3/cmake/cisstQtExternal.cmake"
			],
			"type" : "file"
		},
		{
			"backtrace" : 11,
			"component" : "cisstQt",
			"destination" : "share/cisst-1.3/cmake",
			"paths" : 
			[
				"/home/ytxu/cr_dvrk_ws/build/cisst/share/cisst-1.3/cmake/cisstQtQt5Xml.cmake"
			],
			"type" : "file"
		},
		{
			"backtrace" : 12,
			"component" : "cisstQt",
			"destination" : "share/cisst-1.3/cmake",
			"paths" : 
			[
				"/home/ytxu/cr_dvrk_ws/build/cisst/share/cisst-1.3/cmake/cisstQtExternal.cmake"
			],
			"type" : "file"
		},
		{
			"backtrace" : 14,
			"component" : "cisstQt",
			"destination" : "share/cisst-1.3/cmake",
			"paths" : 
			[
				"/home/ytxu/cr_dvrk_ws/build/cisst/share/cisst-1.3/cmake/cisstQtQt5XmlPatterns.cmake"
			],
			"type" : "file"
		},
		{
			"backtrace" : 15,
			"component" : "cisstQt",
			"destination" : "share/cisst-1.3/cmake",
			"paths" : 
			[
				"/home/ytxu/cr_dvrk_ws/build/cisst/share/cisst-1.3/cmake/cisstQtExternal.cmake"
			],
			"type" : "file"
		},
		{
			"backtrace" : 17,
			"component" : "cisstQt",
			"destination" : "share/cisst-1.3/cmake",
			"paths" : 
			[
				"/home/ytxu/cr_dvrk_ws/build/cisst/share/cisst-1.3/cmake/cisstQtQt5Widgets.cmake"
			],
			"type" : "file"
		},
		{
			"backtrace" : 18,
			"component" : "cisstQt",
			"destination" : "share/cisst-1.3/cmake",
			"paths" : 
			[
				"/home/ytxu/cr_dvrk_ws/build/cisst/share/cisst-1.3/cmake/cisstQtExternal.cmake"
			],
			"type" : "file"
		},
		{
			"backtrace" : 20,
			"component" : "cisstQt",
			"destination" : "share/cisst-1.3/cmake",
			"paths" : 
			[
				"/home/ytxu/cr_dvrk_ws/build/cisst/share/cisst-1.3/cmake/cisstQtQt5Gui.cmake"
			],
			"type" : "file"
		},
		{
			"backtrace" : 21,
			"component" : "cisstQt",
			"destination" : "share/cisst-1.3/cmake",
			"paths" : 
			[
				"/home/ytxu/cr_dvrk_ws/build/cisst/share/cisst-1.3/cmake/cisstQtExternal.cmake"
			],
			"type" : "file"
		},
		{
			"backtrace" : 23,
			"component" : "cisstQt",
			"destination" : "share/cisst-1.3/cmake",
			"paths" : 
			[
				"/home/ytxu/cr_dvrk_ws/build/cisst/share/cisst-1.3/cmake/cisstQtQt5OpenGL.cmake"
			],
			"type" : "file"
		},
		{
			"backtrace" : 24,
			"component" : "cisstQt",
			"destination" : "share/cisst-1.3/cmake",
			"paths" : 
			[
				"/home/ytxu/cr_dvrk_ws/build/cisst/share/cisst-1.3/cmake/cisstQtExternal.cmake"
			],
			"type" : "file"
		},
		{
			"backtrace" : 26,
			"component" : "cisstQt",
			"destination" : "share/cisst-1.3/cmake",
			"paths" : 
			[
				"/home/ytxu/cr_dvrk_ws/build/cisst/share/cisst-1.3/cmake/cisstQtExternal.cmake"
			],
			"type" : "file"
		},
		{
			"backtrace" : 27,
			"component" : "cisstCommon",
			"destination" : "share/cisst-1.3/cmake",
			"paths" : 
			[
				"/home/ytxu/cr_dvrk_ws/build/cisst/share/cisst-1.3/cmake/cisstQtBuild.cmake"
			],
			"type" : "file"
		},
		{
			"backtrace" : 29,
			"component" : "cisstPython",
			"destination" : "share/cisst-1.3/cmake",
			"paths" : 
			[
				"/home/ytxu/cr_dvrk_ws/build/cisst/share/cisst-1.3/cmake/cisstPythonSWIG.cmake"
			],
			"type" : "file"
		},
		{
			"backtrace" : 30,
			"component" : "cisstPython",
			"destination" : "share/cisst-1.3/cmake",
			"paths" : 
			[
				"/home/ytxu/cr_dvrk_ws/build/cisst/share/cisst-1.3/cmake/cisstPythonExternal.cmake"
			],
			"type" : "file"
		},
		{
			"backtrace" : 32,
			"component" : "cisstPython",
			"destination" : "share/cisst-1.3/cmake",
			"paths" : 
			[
				"/home/ytxu/cr_dvrk_ws/build/cisst/share/cisst-1.3/cmake/cisstPythonSWIG.cmake"
			],
			"type" : "file"
		},
		{
			"backtrace" : 33,
			"component" : "cisstPython",
			"destination" : "share/cisst-1.3/cmake",
			"paths" : 
			[
				"/home/ytxu/cr_dvrk_ws/build/cisst/share/cisst-1.3/cmake/cisstPythonExternal.cmake"
			],
			"type" : "file"
		},
		{
			"backtrace" : 35,
			"component" : "cisstPython",
			"destination" : "share/cisst-1.3/cmake",
			"paths" : 
			[
				"/home/ytxu/cr_dvrk_ws/build/cisst/share/cisst-1.3/cmake/cisstPythonPython.cmake"
			],
			"type" : "file"
		},
		{
			"backtrace" : 36,
			"component" : "cisstPython",
			"destination" : "share/cisst-1.3/cmake",
			"paths" : 
			[
				"/home/ytxu/cr_dvrk_ws/build/cisst/share/cisst-1.3/cmake/cisstPythonExternal.cmake"
			],
			"type" : "file"
		},
		{
			"backtrace" : 38,
			"component" : "cisstPython",
			"destination" : "share/cisst-1.3/cmake",
			"paths" : 
			[
				"/home/ytxu/cr_dvrk_ws/build/cisst/share/cisst-1.3/cmake/cisstPythonPython.cmake"
			],
			"type" : "file"
		},
		{
			"backtrace" : 39,
			"component" : "cisstPython",
			"destination" : "share/cisst-1.3/cmake",
			"paths" : 
			[
				"/home/ytxu/cr_dvrk_ws/build/cisst/share/cisst-1.3/cmake/cisstPythonExternal.cmake"
			],
			"type" : "file"
		},
		{
			"backtrace" : 41,
			"component" : "cisstPython",
			"destination" : "share/cisst-1.3/cmake",
			"paths" : 
			[
				"/home/ytxu/cr_dvrk_ws/build/cisst/share/cisst-1.3/cmake/cisstPythonNumPy.cmake"
			],
			"type" : "file"
		},
		{
			"backtrace" : 42,
			"component" : "cisstPython",
			"destination" : "share/cisst-1.3/cmake",
			"paths" : 
			[
				"/home/ytxu/cr_dvrk_ws/build/cisst/share/cisst-1.3/cmake/cisstPythonExternal.cmake"
			],
			"type" : "file"
		},
		{
			"backtrace" : 43,
			"component" : "cisstCommon",
			"destination" : "share/cisst-1.3/cmake",
			"paths" : 
			[
				"/home/ytxu/cr_dvrk_ws/build/cisst/share/cisst-1.3/cmake/cisstPythonBuild.cmake"
			],
			"type" : "file"
		},
		{
			"backtrace" : 45,
			"component" : "cisstCommon",
			"destination" : "share/cisst-1.3/cmake",
			"paths" : 
			[
				"/home/ytxu/cr_dvrk_ws/build/cisst/share/cisst-1.3/cmake/cisstCommonJSON.cmake"
			],
			"type" : "file"
		},
		{
			"backtrace" : 46,
			"component" : "cisstCommon",
			"destination" : "share/cisst-1.3/cmake",
			"paths" : 
			[
				"/home/ytxu/cr_dvrk_ws/build/cisst/share/cisst-1.3/cmake/cisstCommonExternal.cmake"
			],
			"type" : "file"
		},
		{
			"backtrace" : 48,
			"component" : "cisstCommon",
			"destination" : "share/cisst-1.3/cmake",
			"paths" : 
			[
				"/home/ytxu/cr_dvrk_ws/build/cisst/share/cisst-1.3/cmake/cisstCommonJSON.cmake"
			],
			"type" : "file"
		},
		{
			"backtrace" : 49,
			"component" : "cisstCommon",
			"destination" : "share/cisst-1.3/cmake",
			"paths" : 
			[
				"/home/ytxu/cr_dvrk_ws/build/cisst/share/cisst-1.3/cmake/cisstCommonExternal.cmake"
			],
			"type" : "file"
		},
		{
			"backtrace" : 51,
			"component" : "cisstCommon",
			"destination" : "share/cisst-1.3/cmake",
			"paths" : 
			[
				"/home/ytxu/cr_dvrk_ws/build/cisst/share/cisst-1.3/cmake/cisstCommonJSON.cmake"
			],
			"type" : "file"
		},
		{
			"backtrace" : 52,
			"component" : "cisstCommon",
			"destination" : "share/cisst-1.3/cmake",
			"paths" : 
			[
				"/home/ytxu/cr_dvrk_ws/build/cisst/share/cisst-1.3/cmake/cisstCommonExternal.cmake"
			],
			"type" : "file"
		}
	],
	"paths" : 
	{
		"build" : "cisst-dependencies",
		"source" : "cisst-dependencies"
	}
}
